{
  "options_selected": {
    "assertividadeMin": 0,
    "assertividade_radio": "todas_empresas",
    "bairro": [],
    "capSocialAte": 0,
    "capSocialDe": 100000000,
    "cep": "",
    "checkEmail": false,
    "checkEmailBuscado": false,
    "checkExact": false,
    "checkExportado": false,
    "checkQualificacao": false,
    "checkValidado": false,
    "checkVisualizada": false,
    "cidades": [],
    "cidadesExclude": [],
    "classificacao_juridica": [],
    "cnaes": [],
    "cnaesSecundariosExcluidos": [],
    "cnaesSecundariosIncluidos": [],
    "comRedesSociais": "todas_empresas",
    "comSocios": false,
    "comTelefones": false,
    "comercioExterior": {
      "acoes": [],
      "anoAte": "",
      "anoDe": ""
    },
    "dataAberturaAte": "",
    "dataAberturaDe": "",
    "dataAcaoAte": "",
    "dataAcaoDe": "",
    "dataExclusaoAte": "",
    "dataExclusaoDe": "",
    "dataInclusaoAte": "",
    "dataInclusaoDe": "",
    "dataSituacaoAte": "",
    "dataSituacaoDe": "",
    "decisores": {},
    "emailBuscado": false,
    "emailGerado": false,
    "enquadramento_de_porte": [],
    "excludedAutoTagsMode": "any",
    "excludedCnaes": [],
    "excludedTagIds": [],
    "excludedTagNames": [],
    "excluirNomeEmpresa": true,
    "excluirPalavra": [],
    "excluirProdutosServicos": true,
    "exportado": false,
    "exportadoExact": false,
    "faturamento_ate": 999999999999999,
    "faturamento_de": "0",
    "ferramentas": [],
    "includedAutoTagsMode": "any",
    "incluirFiliais": false,
    "incluirGrupoEconomico": false,
    "incluirInativas": false,
    "incluirNomeEmpresa": true,
    "incluirProdutosServicos": true,
    "incluirRecuperacaoJudicial": false,
    "listCNPJs": "䀀",
    "logradouro": "",
    "natureza_juridica": [],
    "ncms": [],
    "nivelAtividade": 0,
    "nivelDecisao": [],
    "nomeSocio": "",
    "nomeSocioTipoPesquisa": false,
    "numeroEndAte": "",
    "numeroEndDe": "",
    "optante_pelo_simples": [],
    "origem": "busca",
    "palavraChave": [],
    "pat": {},
    "portes": [],
    "qtdFiliaisAte": "",
    "qtdFiliaisDe": "",
    "qtdFuncionariosDe": 200,
    "qtd_funcionarios_ate": 999999999,
    "qtd_funcionarios_de": 200,
    "qualificado": false,
    "recebimentosGovFederal": 0,
    "redesSociais": [],
    "redesSociaisModo": "qualquer",
    "regimeTributarioAtual": [],
    "regioes": [],
    "saudeFinanceira": {
      "apenasSemDividas": false,
      "dataAte": "",
      "dataDe": "",
      "origem": [],
      "percentualAte": "",
      "percentualDe": "",
      "valorAte": 0,
      "valorDe": 0
    },
    "selectedTagIds": [],
    "selectedTagsNames": [],
    "setoresAmigaveis": [
      "Agricultura",
      "Alimentos",
      "Cosméticos",
      "Indústrias da transformação",
      "Logística e Transporte",
      "Manufatura",
      "Produtos farmacêuticos",
      "Construção"
    ],
    "situacaoCadastral": ["ATIVA"],
    "tecnologias": [],
    "telefoneValidado": false,
    "ufs": [],
    "ufsExclude": [],
    "variacaoFuncionarios": [],
    "visualizada": false
  },
  "size": 10,
  "sortObject": [
    { "score_total": { "order": "desc" } },
    { "cd_cnpj.keyword": { "order": "desc" } }
  ],
  "source": ["cd_cnpj"]
}
